cocrawler/__init__.py
cocrawler/accumulator.py
cocrawler/burner.py
cocrawler/config.py
cocrawler/content.py
cocrawler/datalayer.py
cocrawler/dns.py
cocrawler/facet.py
cocrawler/fetcher.py
cocrawler/geoip.py
cocrawler/hostdomain.py
cocrawler/memory.py
cocrawler/parse.py
cocrawler/pdeathsig.py
cocrawler/post_fetch.py
cocrawler/pre_fetch.py
cocrawler/robots.py
cocrawler/scheduler.py
cocrawler/seeds.py
cocrawler/stats.py
cocrawler/surt.py
cocrawler/timebin.py
cocrawler/timer.py
cocrawler/topk.py
cocrawler/url_allowed.py
cocrawler/urls.py
cocrawler/useragent.py
cocrawler/warc.py
cocrawler/webserver.py
cocrawler-0.1.14.data/scripts/aiohttp-fetch.py
cocrawler-0.1.14.data/scripts/bench_burner.py
cocrawler-0.1.14.data/scripts/bench_dns.py
cocrawler-0.1.14.data/scripts/cocrawler-savefile-dump.py
cocrawler-0.1.14.data/scripts/crawl.py
cocrawler-0.1.14.data/scripts/parse-html.py
cocrawler-0.1.14.data/scripts/run_burner.py
cocrawler-0.1.14.data/scripts/run_burner_bench.py
cocrawler-0.1.14.data/scripts/run_parsers.py
cocrawler-0.1.14.dist-info/LICENSE
cocrawler-0.1.14.dist-info/METADATA
cocrawler-0.1.14.dist-info/WHEEL
cocrawler-0.1.14.dist-info/top_level.txt
cocrawler-0.1.14.dist-info/RECORD
