Metadata-Version: 2.1
Name: cocrawler
Version: 0.1.14
Summary: A modern web crawler framework for Python
Home-page: https://github.com/cocrawler/cocrawler
Author: Greg Lindahl and others
Author-email: lindahl@pbm.com
License: Apache 2.0
Platform: UNKNOWN
Classifier: Development Status :: 2 - Pre-Alpha
Classifier: Environment :: Console
Classifier: Operating System :: POSIX :: Linux
Classifier: Environment :: MacOS X
Classifier: Framework :: AsyncIO
Classifier: Intended Audience :: Information Technology
Classifier: Intended Audience :: Developers
Classifier: Natural Language :: English
Classifier: License :: OSI Approved :: Apache Software License
Classifier: Programming Language :: Python
Classifier: Programming Language :: Python :: 3.6
Classifier: Programming Language :: Python :: 3.7
Classifier: Programming Language :: Python :: 3.8
Classifier: Programming Language :: Python :: 3 :: Only
Requires-Python: >=3.6.3
Requires-Dist: uvloop
Requires-Dist: aiohttp
Requires-Dist: yarl
Requires-Dist: aiodns
Requires-Dist: pyyaml
Requires-Dist: cchardet
Requires-Dist: surt
Requires-Dist: reppy
Requires-Dist: cachetools
Requires-Dist: tldextract (>=3)
Requires-Dist: sortedcontainers
Requires-Dist: sortedcollections
Requires-Dist: psutil
Requires-Dist: hdrhistogram
Requires-Dist: beautifulsoup4
Requires-Dist: lxml
Requires-Dist: extensions
Requires-Dist: warcio
Requires-Dist: geoip2
Requires-Dist: objgraph
Requires-Dist: brotlipy
Requires-Dist: setuptools-scm
Provides-Extra: test
Requires-Dist: bottle ; extra == 'test'
Requires-Dist: pytest (>=3.0.0) ; extra == 'test'
Requires-Dist: pytest-cov ; extra == 'test'
Requires-Dist: pytest-asyncio ; extra == 'test'
